Zips/Zips.py
Zips/__init__.py
Zips/__main__.py
Zips-1.0.0.dist-info/LICENSE
Zips-1.0.0.dist-info/METADATA
Zips-1.0.0.dist-info/WHEEL
Zips-1.0.0.dist-info/top_level.txt
Zips-1.0.0.dist-info/RECORD
