Metadata-Version: 2.1
Name: Zips
Version: 1.0.0
Summary: Compress / Extract six kinds of compression software formats easily
Home-page: https://github.com/ala98412/Zips
Author: Jui-Hung, Tai
Author-email: ala98412@gmail.com
License: MIT
Platform: UNKNOWN
Requires-Python: >=2.7
